grappelli_safe/__init__.py
grappelli_safe/locale/ar/LC_MESSAGES/django.mo
grappelli_safe/locale/ar/LC_MESSAGES/django.po
grappelli_safe/locale/de/LC_MESSAGES/django.mo
grappelli_safe/locale/de/LC_MESSAGES/django.po
grappelli_safe/locale/es/LC_MESSAGES/django.mo
grappelli_safe/locale/es/LC_MESSAGES/django.po
grappelli_safe/locale/nb/LC_MESSAGES/django.mo
grappelli_safe/locale/nb/LC_MESSAGES/django.po
grappelli_safe/locale/pt_BR/LC_MESSAGES/django.mo
grappelli_safe/locale/pt_BR/LC_MESSAGES/django.po
grappelli_safe/static/admin/js/actions.js
grappelli_safe/static/admin/js/actions.min.js
grappelli_safe/static/grappelli/css/base.css
grappelli_safe/static/grappelli/css/changelist.css
grappelli_safe/static/grappelli/css/dashboard.css
grappelli_safe/static/grappelli/css/forms.css
grappelli_safe/static/grappelli/css/login.css
grappelli_safe/static/grappelli/css/modules.css
grappelli_safe/static/grappelli/css/reset.css
grappelli_safe/static/grappelli/css/rtl.css
grappelli_safe/static/grappelli/css/tables.css
grappelli_safe/static/grappelli/css/typography.css
grappelli_safe/static/grappelli/css/webkit-gradients.css
grappelli_safe/static/grappelli/css/widgets.css
grappelli_safe/static/grappelli/img/grappelli-icon.png
grappelli_safe/static/grappelli/img/icon_calendar.gif
grappelli_safe/static/grappelli/img/icon_clock.gif
grappelli_safe/static/grappelli/img/admin/arrow-down.gif
grappelli_safe/static/grappelli/img/admin/arrow-up.gif
grappelli_safe/static/grappelli/img/admin/changelist-bg.gif
grappelli_safe/static/grappelli/img/admin/changelist-bg_rtl.gif
grappelli_safe/static/grappelli/img/admin/chooser-bg.gif
grappelli_safe/static/grappelli/img/admin/chooser_stacked-bg.gif
grappelli_safe/static/grappelli/img/admin/default-bg-reverse.gif
grappelli_safe/static/grappelli/img/admin/default-bg.gif
grappelli_safe/static/grappelli/img/admin/deleted-overlay.gif
grappelli_safe/static/grappelli/img/admin/icon-no.gif
grappelli_safe/static/grappelli/img/admin/icon-unknown.gif
grappelli_safe-1.1.1.dist-info/LICENSE
grappelli_safe-1.1.1.dist-info/METADATA
grappelli_safe-1.1.1.dist-info/WHEEL
grappelli_safe-1.1.1.dist-info/top_level.txt
grappelli_safe-1.1.1.dist-info/RECORD
