Metadata-Version: 2.1
Name: grappelli_safe
Version: 1.1.1
Summary: A snapshot of the grappelli_2 branch of django-grappelli, packaged as a dependency for the Mezzanine CMS for Django.
Home-page: http://github.com/stephenmcd/grappelli-safe
Author: Patrick Kranzlmueller, Axel Swoboda (vonautomatisch)
Author-email: werkstaetten@vonautomatisch.at
Maintainer: Stephen McDonald
Maintainer-email: stephen.mc@gmail.com
License: UNKNOWN
Platform: UNKNOWN
Classifier: Programming Language :: Python
Classifier: Programming Language :: Python :: 3
Classifier: Programming Language :: Python :: 3.6
Classifier: Programming Language :: Python :: 3.7
Classifier: Programming Language :: Python :: 3.8
Classifier: Programming Language :: Python :: 3.9
Classifier: Programming Language :: Python :: 3.10
Requires-Python: >=3.6
License-File: LICENSE
